codescan/__init__.py
codescan/__main__.py
codescan/file.py
codescan/patterns.py
codescan/print.py
codescan/scan.py
codescan-0.2.0.dist-info/METADATA
codescan-0.2.0.dist-info/WHEEL
codescan-0.2.0.dist-info/top_level.txt
codescan-0.2.0.dist-info/RECORD
