Metadata-Version: 2.1
Name: codescan
Version: 0.2.0
Summary: Scans the code for security leaks
Home-page: https://github.com/atparinas/codescan
Author: Andy Parinas
Author-email: andy.parinas@gmail.com
License: MIT
Platform: UNKNOWN
Requires-Dist: prettytable
Requires-Dist: progress
